rwave/__init__.py
rwave/convert.py
rwave/rwave.py
rwave/wave_io.py
rwave-0.1.2.dist-info/LICENSE
rwave-0.1.2.dist-info/METADATA
rwave-0.1.2.dist-info/WHEEL
rwave-0.1.2.dist-info/top_level.txt
rwave-0.1.2.dist-info/RECORD
